Perceptron/__init__.py
Perceptron/perceptron.py
pythonPackaging_Rushik2900-0.0.8.dist-info/LICENSE
pythonPackaging_Rushik2900-0.0.8.dist-info/METADATA
pythonPackaging_Rushik2900-0.0.8.dist-info/WHEEL
pythonPackaging_Rushik2900-0.0.8.dist-info/top_level.txt
pythonPackaging_Rushik2900-0.0.8.dist-info/RECORD
