Metadata-Version: 2.1
Name: pythonPackaging-Rushik2900
Version: 0.0.8
Summary: Its an implementation of perceptron
Home-page: https://github.com/Rushik2900/pythonPackaging
Author: Rushik2900
Author-email: rush2900@gmail.com
Classifier: Programming Language :: Python :: 3
Classifier: License :: OSI Approved :: MIT License
Classifier: Operating System :: OS Independent
Requires-Python: >=3.7
License-File: LICENSE
Requires-Dist: numpy
Requires-Dist: tqdm
